{"config": {"view": {"continuousWidth": 300, "continuousHeight": 300}}, "vconcat": [{"data": {"name": "data-ab4a85c7637904626c05a17b0e5b49ec"}, "mark": {"type": "rect"}, "encoding": {"color": {"field": "value", "scale": {"scheme": "viridis", "type": "log"}, "title": "Percent in %", "type": "quantitative"}, "opacity": {"condition": {"param": "param_15", "value": 1}, "value": 0.25}, "tooltip": [{"field": "pdf_letters", "title": "PDF", "type": "ordinal"}, {"field": "ocr_letters", "title": "OCR", "type": "ordinal"}, {"field": "name", "title": "Percentage", "type": "nominal"}, {"field": "Total Count of PDF token", "title": "Count", "type": "quantitative"}], "x": {"field": "ocr_letters", "sort": ["'\\\\t'", "'\\\\n'", " ", "'\\\\xa0'", "'\\\\xad'", "\u00b1", "\u00c2", "\u00c5", "\u00d6", "\u00d7", "\u00e0", "\u00e1", "\u00e4", "\u00e8", "\u00e9", "\u00ed", "\u00f1", "\u00f3", "\u00f4", "\u00f6", "\u00f8", "\u00fc", "\u0107", "\u0142", "\u0144", "\u017a", "\u0307", "\u0393", "\u0394", "\u03a9", "\u03b1", "\u03b2", "\u03b3", "\u03b4", "\u03b8", "\u03bb", "\u03bc", "\u03bd", "\u03c0", "\u03c1", "\u03c3", "\u03c4", "\u03c7", "\u2013", "\u2014", "\u201c", "\u201d", "\u2218", "\u223c", "\u2248", "\u2264", "\u2299", "\u27e8", "!", "\"", "$", "%", "&", "'", "(", ")", "*", "+", ",", "-", ".", "/", "0", "1", "2", "3", "4", "5", "6", "7", "8", "9", ":", ";", "<", "=", ">", "?", "A", "B", "C", "D", "E", "F", "G", "H", "I", "INSERT", "J", "K", "L", "M", "N", "O", "P", "Q", "R", "S", "T", "U", "V", "W", "X", "Y", "Z", "[", "'\\\\\\\\'", "]", "a", "b", "c", "d", "e", "f", "g", "h", "i", "j", "k", "l", "m", "n", "o", "p", "q", "r", "s", "t", "u", "v", "w", "x", "y", "z", "{", "|", "}", "~", "\u00a2", "\u00a3", "\u00ab", "\u00b0", "\u00bb", "\u00c0", "\u00c1", "\u0391", "\u0395", "\u0397", "\u0399", "\u039c", "\u039f", "\u03a0", "\u03a4", "\u03b5", "\u03b7", "\u03b9", "\u03bf", "\u03c2", "\u03c5", "\u03c9", "\u2018", "\u2019", "\u20ac", "\u2122", "\u2191", "\u2193", "\u2194", "\u2195", "\u2196", "\u2197", "\u2198", "\u2199", "\u21a5", "\u21a7", "\u21a9", "\u21b1", "\u21b2", "\u21b4", "\u21b5", "\u21b8", "\u21bb", "\u21bd", "\u21be", "\u21bf", "\u21c0", "\u21c1", "\u21c2", "\u2201", "\u220e", "\u220f", "\u2210", "\u2211", "\u2212", "\u2215", "\u2216", "\u2219", "\u221f", "\u2220", "\u2222", "\u2223", "\u2225", "\u2229", "\u222a", "\u222b", "\u2236", "\u2240", "\u225f", "\u226f", "\u2271", "\u2278", "\u227a", "\u227b", "\u227c", "\u2280", "\u2290", "\u2293", "\u2294", "\u22a5", "\u22b0", "\u22b2", "\u22b3", "\u22ba", "\u22bd", "\u22be", "\u22c0", "\u22c1", "\u22c3", "\u22c5", "\u22cf", "\u22d6", "\u22dc", "\u22dd", "\u22df", "\u22e1", "\u22ee", "\u22ef"], "title": "OCR Characters", "type": "ordinal"}, "y": {"field": "pdf_letters", "sort": ["'\\\\t'", "'\\\\n'", " ", "'\\\\xa0'", "'\\\\xad'", "\u00b1", "\u00c2", "\u00c5", "\u00d6", "\u00d7", "\u00e0", "\u00e1", "\u00e4", "\u00e8", "\u00e9", "\u00ed", "\u00f1", "\u00f3", "\u00f4", "\u00f6", "\u00f8", "\u00fc", "\u0107", "\u0142", "\u0144", "\u017a", "\u0307", "\u0393", "\u0394", "\u03a9", "\u03b1", "\u03b2", "\u03b3", "\u03b4", "\u03b8", "\u03bb", "\u03bc", "\u03bd", "\u03c0", "\u03c1", "\u03c3", "\u03c4", "\u03c7", "\u2013", "\u2014", "\u201c", "\u201d", "\u2218", "\u223c", "\u2248", "\u2264", "\u2299", "\u27e8"], "title": "PDF Characters", "type": "ordinal"}}, "height": 350, "name": "view_8", "transform": [{"fold": ["% of all OCR tokens", "Total Count of PDF token"], "as": ["column", "value"]}, {"filter": {"param": "param_16"}}], "width": 1200}, {"hconcat": [{"data": {"name": "data-081e3fbf9b638105f2f44dea079b8589"}, "mark": {"type": "text", "size": 20, "stroke": "black"}, "encoding": {"text": {"field": "label", "type": "nominal"}, "x": {"axis": {"grid": false}}, "y": {"axis": {"grid": false}}}, "height": 1, "transform": [{"calculate": "datum.Total", "as": "label"}], "width": 1}, {"data": {"name": "data-ab4a85c7637904626c05a17b0e5b49ec"}, "mark": {"type": "text", "size": 20, "stroke": "black", "text": " "}, "encoding": {"text": {"condition": {"param": "param_15", "value": " "}, "field": "label", "type": "nominal"}, "y": {"axis": {"grid": false, "gridColor": "white"}}}, "height": 1, "transform": [{"filter": {"param": "param_15"}}, {"aggregate": [{"op": "sum", "field": "% of all OCR tokens", "as": "total"}]}, {"calculate": "format(datum.total,\".2f\") + \"%\"", "as": "label"}], "width": 1}]}], "center": true, "params": [{"name": "param_15", "select": {"type": "point", "encodings": ["x", "y"]}, "views": ["view_8"]}, {"name": "param_16", "select": {"type": "point", "fields": ["column"]}, "bind": {"input": "select", "options": ["% of all OCR tokens", "Total Count of PDF token"], "name": "Color by: "}, "value": "% of all OCR tokens", "views": ["view_8"]}], "$schema": "https://vega.github.io/schema/vega-lite/v5.6.1.json", "datasets": {"data-ab4a85c7637904626c05a17b0e5b49ec": [{"pdf_letters": " ", "ocr_letters": " ", "% of all OCR tokens": 97.94224675650194, "Total Count of PDF token": 66373539, "name": "97.94%"}, {"pdf_letters": " ", "ocr_letters": "C", "% of all OCR tokens": 0.0041981442638194715, "Total Count of PDF token": 2845, "name": "0.0%"}, {"pdf_letters": " ", "ocr_letters": "?", "% of all OCR tokens": 0.010304267625395913, "Total Count of PDF token": 6983, "name": "0.01%"}, {"pdf_letters": " ", "ocr_letters": "INSERT", "% of all OCR tokens": 1.1910083629689854, "Total Count of PDF token": 807123, "name": "1.19%"}, {"pdf_letters": " ", "ocr_letters": "7", "% of all OCR tokens": 0.021005477537950856, "Total Count of PDF token": 14235, "name": "0.02%"}, {"pdf_letters": " ", "ocr_letters": "a", "% of all OCR tokens": 0.018058660632907803, "Total Count of PDF token": 12238, "name": "0.02%"}, {"pdf_letters": " ", "ocr_letters": "4", "% of all OCR tokens": 0.017154104417188527, "Total Count of PDF token": 11625, "name": "0.02%"}, {"pdf_letters": " ", "ocr_letters": "P", "% of all OCR tokens": 0.0021662129276931404, "Total Count of PDF token": 1468, "name": "0.0%"}, {"pdf_letters": " ", "ocr_letters": "\u2014", "% of all OCR tokens": 0.00745926863044198, "Total Count of PDF token": 5055, "name": "0.01%"}, {"pdf_letters": " ", "ocr_letters": ".", "% of all OCR tokens": 0.027564616818329606, "Total Count of PDF token": 18680, "name": "0.03%"}, {"pdf_letters": " ", "ocr_letters": "\"", "% of all OCR tokens": 0.004803149236812788, "Total Count of PDF token": 3255, "name": "0.0%"}, {"pdf_letters": " ", "ocr_letters": "5", "% of all OCR tokens": 0.020149616844448118, "Total Count of PDF token": 13655, "name": "0.02%"}, {"pdf_letters": " ", "ocr_letters": "6", "% of all OCR tokens": 0.009966350213650865, "Total Count of PDF token": 6754, "name": "0.01%"}, {"pdf_letters": " ", "ocr_letters": "m", "% of all OCR tokens": 0.004561147247615462, "Total Count of PDF token": 3091, "name": "0.0%"}, {"pdf_letters": " ", "ocr_letters": "k", "% of all OCR tokens": 0.0012070587022159325, "Total Count of PDF token": 818, "name": "0.0%"}, {"pdf_letters": " ", "ocr_letters": "Y", "% of all OCR tokens": 0.0005843462665984222, "Total Count of PDF token": 396, "name": "0.0%"}, {"pdf_letters": " ", "ocr_letters": "K", "% of all OCR tokens": 0.0005400776100379356, "Total Count of PDF token": 366, "name": "0.0%"}, {"pdf_letters": " ", "ocr_letters": "1", "% of all OCR tokens": 0.0418914297031884, "Total Count of PDF token": 28389, "name": "0.04%"}, {"pdf_letters": " ", "ocr_letters": "+", "% of all OCR tokens": 0.0033245761076925377, "Total Count of PDF token": 2253, "name": "0.0%"}, {"pdf_letters": " ", "ocr_letters": "x", "% of all OCR tokens": 0.00436931640252002, "Total Count of PDF token": 2961, "name": "0.0%"}, {"pdf_letters": " ", "ocr_letters": "~", "% of all OCR tokens": 0.0046216477449147935, "Total Count of PDF token": 3132, "name": "0.0%"}, {"pdf_letters": " ", "ocr_letters": "2", "% of all OCR tokens": 0.029842977009309313, "Total Count of PDF token": 20224, "name": "0.03%"}, {"pdf_letters": " ", "ocr_letters": "*", "% of all OCR tokens": 0.0008957024844071772, "Total Count of PDF token": 607, "name": "0.0%"}, {"pdf_letters": " ", "ocr_letters": ")", "% of all OCR tokens": 0.07960242260518152, "Total Count of PDF token": 53945, "name": "0.08%"}, {"pdf_letters": " ", "ocr_letters": "0", "% of all OCR tokens": 0.016478269593698434, "Total Count of PDF token": 11167, "name": "0.02%"}, {"pdf_letters": " ", "ocr_letters": "3", "% of all OCR tokens": 0.017698608892882512, "Total Count of PDF token": 11994, "name": "0.02%"}, {"pdf_letters": " ", "ocr_letters": "j", "% of all OCR tokens": 0.0031002815811194064, "Total Count of PDF token": 2101, "name": "0.0%"}, {"pdf_letters": " ", "ocr_letters": "L", "% of all OCR tokens": 0.012166502444707046, "Total Count of PDF token": 8245, "name": "0.01%"}, {"pdf_letters": " ", "ocr_letters": "t", "% of all OCR tokens": 0.012229954185777075, "Total Count of PDF token": 8288, "name": "0.01%"}, {"pdf_letters": " ", "ocr_letters": "H", "% of all OCR tokens": 0.003258173122851808, "Total Count of PDF token": 2208, "name": "0.0%"}, {"pdf_letters": " ", "ocr_letters": "F", "% of all OCR tokens": 0.0016349890489673023, "Total Count of PDF token": 1108, "name": "0.0%"}, {"pdf_letters": " ", "ocr_letters": "E", "% of all OCR tokens": 0.002515935314520984, "Total Count of PDF token": 1705, "name": "0.0%"}, {"pdf_letters": " ", "ocr_letters": "-", "% of all OCR tokens": 0.007234974103868847, "Total Count of PDF token": 4903, "name": "0.01%"}, {"pdf_letters": " ", "ocr_letters": "r", "% of all OCR tokens": 0.012046977071993733, "Total Count of PDF token": 8164, "name": "0.01%"}, {"pdf_letters": " ", "ocr_letters": ",", "% of all OCR tokens": 0.0029807562084060925, "Total Count of PDF token": 2020, "name": "0.0%"}, {"pdf_letters": " ", "ocr_letters": "M", "% of all OCR tokens": 0.0032139044662913216, "Total Count of PDF token": 2178, "name": "0.0%"}, {"pdf_letters": " ", "ocr_letters": "A", "% of all OCR tokens": 0.01195401289321671, "Total Count of PDF token": 8101, "name": "0.01%"}, {"pdf_letters": " ", "ocr_letters": "p", "% of all OCR tokens": 0.005964463660582884, "Total Count of PDF token": 4042, "name": "0.01%"}, {"pdf_letters": " ", "ocr_letters": "c", "% of all OCR tokens": 0.009628432801905819, "Total Count of PDF token": 6525, "name": "0.01%"}, {"pdf_letters": " ", "ocr_letters": "g", "% of all OCR tokens": 0.004326523367844883, "Total Count of PDF token": 2932, "name": "0.0%"}, {"pdf_letters": " ", "ocr_letters": "S", "% of all OCR tokens": 0.00417158306988318, "Total Count of PDF token": 2827, "name": "0.0%"}, {"pdf_letters": " ", "ocr_letters": "n", "% of all OCR tokens": 0.012901362143611124, "Total Count of PDF token": 8743, "name": "0.01%"}, {"pdf_letters": " ", "ocr_letters": "e", "% of all OCR tokens": 0.018628250680652728, "Total Count of PDF token": 12624, "name": "0.02%"}, {"pdf_letters": " ", "ocr_letters": "w", "% of all OCR tokens": 0.0023668975041006794, "Total Count of PDF token": 1604, "name": "0.0%"}, {"pdf_letters": " ", "ocr_letters": "D", "% of all OCR tokens": 0.003113562178087552, "Total Count of PDF token": 2110, "name": "0.0%"}, {"pdf_letters": " ", "ocr_letters": "I", "% of all OCR tokens": 0.010791222847561266, "Total Count of PDF token": 7313, "name": "0.01%"}, {"pdf_letters": " ", "ocr_letters": "y", "% of all OCR tokens": 0.005279775105780693, "Total Count of PDF token": 3578, "name": "0.01%"}, {"pdf_letters": " ", "ocr_letters": "9", "% of all OCR tokens": 0.014819670594565537, "Total Count of PDF token": 10043, "name": "0.01%"}, {"pdf_letters": " ", "ocr_letters": "8", "% of all OCR tokens": 0.009768616881014026, "Total Count of PDF token": 6620, "name": "0.01%"}, {"pdf_letters": " ", "ocr_letters": "V", "% of all OCR tokens": 0.001612854720687059, "Total Count of PDF token": 1093, "name": "0.0%"}, {"pdf_letters": " ", "ocr_letters": "G", "% of all OCR tokens": 0.0014239751193623165, "Total Count of PDF token": 965, "name": "0.0%"}, {"pdf_letters": " ", "ocr_letters": "i", "% of all OCR tokens": 0.018944033764117532, "Total Count of PDF token": 12838, "name": "0.02%"}, {"pdf_letters": " ", "ocr_letters": "T", "% of all OCR tokens": 0.005113029832736193, "Total Count of PDF token": 3465, "name": "0.01%"}, {"pdf_letters": " ", "ocr_letters": ">", "% of all OCR tokens": 0.0009045562157192746, "Total Count of PDF token": 613, "name": "0.0%"}, {"pdf_letters": " ", "ocr_letters": "o", "% of all OCR tokens": 0.018976497445595222, "Total Count of PDF token": 12860, "name": "0.02%"}, {"pdf_letters": " ", "ocr_letters": "l", "% of all OCR tokens": 0.017285434764984637, "Total Count of PDF token": 11714, "name": "0.02%"}, {"pdf_letters": " ", "ocr_letters": "s", "% of all OCR tokens": 0.011453777074083214, "Total Count of PDF token": 7762, "name": "0.01%"}, {"pdf_letters": " ", "ocr_letters": "d", "% of all OCR tokens": 0.005968890526238933, "Total Count of PDF token": 4045, "name": "0.01%"}, {"pdf_letters": " ", "ocr_letters": "\u00bb", "% of all OCR tokens": 0.0010122766133497919, "Total Count of PDF token": 686, "name": "0.0%"}, {"pdf_letters": " ", "ocr_letters": "v", "% of all OCR tokens": 0.004372267646290719, "Total Count of PDF token": 2963, "name": "0.0%"}, {"pdf_letters": " ", "ocr_letters": "\u2210", "% of all OCR tokens": 0.011794645729598959, "Total Count of PDF token": 7993, "name": "0.01%"}, {"pdf_letters": " ", "ocr_letters": "\u2195", "% of all OCR tokens": 0.00979075120929427, "Total Count of PDF token": 6635, "name": "0.01%"}, {"pdf_letters": " ", "ocr_letters": "\u2229", "% of all OCR tokens": 0.001596622879948214, "Total Count of PDF token": 1082, "name": "0.0%"}, {"pdf_letters": " ", "ocr_letters": "'\\\\\\\\'", "% of all OCR tokens": 0.00026413631747756956, "Total Count of PDF token": 179, "name": "0.0%"}, {"pdf_letters": " ", "ocr_letters": "Q", "% of all OCR tokens": 0.00075551840529897, "Total Count of PDF token": 512, "name": "0.0%"}, {"pdf_letters": " ", "ocr_letters": "W", "% of all OCR tokens": 0.0011819731301649901, "Total Count of PDF token": 801, "name": "0.0%"}, {"pdf_letters": " ", "ocr_letters": "O", "% of all OCR tokens": 0.005864121372379115, "Total Count of PDF token": 3974, "name": "0.01%"}, {"pdf_letters": " ", "ocr_letters": "\u00a3", "% of all OCR tokens": 0.001395938303540675, "Total Count of PDF token": 946, "name": "0.0%"}, {"pdf_letters": " ", "ocr_letters": "\u03a0", "% of all OCR tokens": 0.001103765170241464, "Total Count of PDF token": 748, "name": "0.0%"}, {"pdf_letters": " ", "ocr_letters": "\u03c0", "% of all OCR tokens": 0.00038366169019088316, "Total Count of PDF token": 260, "name": "0.0%"}, {"pdf_letters": " ", "ocr_letters": "u", "% of all OCR tokens": 0.01281282483049015, "Total Count of PDF token": 8683, "name": "0.01%"}, {"pdf_letters": " ", "ocr_letters": "z", "% of all OCR tokens": 0.002030455714240982, "Total Count of PDF token": 1376, "name": "0.0%"}, {"pdf_letters": " ", "ocr_letters": "\u03bd", "% of all OCR tokens": 0.0006596029827512492, "Total Count of PDF token": 447, "name": "0.0%"}, {"pdf_letters": " ", "ocr_letters": "\u03b1", "% of all OCR tokens": 0.0012690348214006136, "Total Count of PDF token": 860, "name": "0.0%"}, {"pdf_letters": " ", "ocr_letters": "\u00b0", "% of all OCR tokens": 0.0023565681509032325, "Total Count of PDF token": 1597, "name": "0.0%"}, {"pdf_letters": " ", "ocr_letters": "\u2219", "% of all OCR tokens": 0.0028656577013488273, "Total Count of PDF token": 1942, "name": "0.0%"}, {"pdf_letters": " ", "ocr_letters": "\u222a", "% of all OCR tokens": 0.004937430828379597, "Total Count of PDF token": 3346, "name": "0.0%"}, {"pdf_letters": " ", "ocr_letters": "\u2196", "% of all OCR tokens": 0.002358043772788582, "Total Count of PDF token": 1598, "name": "0.0%"}, {"pdf_letters": " ", "ocr_letters": "\u21b8", "% of all OCR tokens": 0.005710656696302762, "Total Count of PDF token": 3870, "name": "0.01%"}, {"pdf_letters": " ", "ocr_letters": "\u21bd", "% of all OCR tokens": 0.002670875612482687, "Total Count of PDF token": 1810, "name": "0.0%"}, {"pdf_letters": " ", "ocr_letters": "\u2290", "% of all OCR tokens": 0.000174123382471247, "Total Count of PDF token": 118, "name": "0.0%"}, {"pdf_letters": " ", "ocr_letters": "\u220f", "% of all OCR tokens": 0.0019522477543174558, "Total Count of PDF token": 1323, "name": "0.0%"}, {"pdf_letters": " ", "ocr_letters": "\u2216", "% of all OCR tokens": 0.01445371636699885, "Total Count of PDF token": 9795, "name": "0.01%"}, {"pdf_letters": " ", "ocr_letters": "\u22be", "% of all OCR tokens": 0.0011967293490184857, "Total Count of PDF token": 811, "name": "0.0%"}, {"pdf_letters": " ", "ocr_letters": "\u22b3", "% of all OCR tokens": 0.0033083442669536926, "Total Count of PDF token": 2242, "name": "0.0%"}, {"pdf_letters": " ", "ocr_letters": "\u227c", "% of all OCR tokens": 0.0033629422767116265, "Total Count of PDF token": 2279, "name": "0.0%"}, {"pdf_letters": " ", "ocr_letters": "\u21b4", "% of all OCR tokens": 0.008660424845116513, "Total Count of PDF token": 5869, "name": "0.01%"}, {"pdf_letters": " ", "ocr_letters": "\u21a5", "% of all OCR tokens": 0.003967947249704942, "Total Count of PDF token": 2689, "name": "0.0%"}, {"pdf_letters": " ", "ocr_letters": "\u22dc", "% of all OCR tokens": 0.005034821872812668, "Total Count of PDF token": 3412, "name": "0.01%"}, {"pdf_letters": " ", "ocr_letters": ":", "% of all OCR tokens": 0.00246428854853375, "Total Count of PDF token": 1670, "name": "0.0%"}, {"pdf_letters": " ", "ocr_letters": "\u22c5", "% of all OCR tokens": 0.008325458677142166, "Total Count of PDF token": 5642, "name": "0.01%"}, {"pdf_letters": " ", "ocr_letters": "\u2222", "% of all OCR tokens": 0.0015494029796170282, "Total Count of PDF token": 1050, "name": "0.0%"}, {"pdf_letters": " ", "ocr_letters": "\u21c2", "% of all OCR tokens": 0.0017855024812729564, "Total Count of PDF token": 1210, "name": "0.0%"}, {"pdf_letters": " ", "ocr_letters": "\u227b", "% of all OCR tokens": 0.0015287442732221344, "Total Count of PDF token": 1036, "name": "0.0%"}, {"pdf_letters": " ", "ocr_letters": "\u2193", "% of all OCR tokens": 0.003931056702571203, "Total Count of PDF token": 2664, "name": "0.0%"}, {"pdf_letters": " ", "ocr_letters": "/", "% of all OCR tokens": 0.0036433104349280414, "Total Count of PDF token": 2469, "name": "0.0%"}, {"pdf_letters": " ", "ocr_letters": "U", "% of all OCR tokens": 0.0012100099459866316, "Total Count of PDF token": 820, "name": "0.0%"}, {"pdf_letters": " ", "ocr_letters": "\u03c5", "% of all OCR tokens": 0.0001652696511591497, "Total Count of PDF token": 112, "name": "0.0%"}, {"pdf_letters": " ", "ocr_letters": "(", "% of all OCR tokens": 0.004444573118672847, "Total Count of PDF token": 3012, "name": "0.0%"}, {"pdf_letters": " ", "ocr_letters": "X", "% of all OCR tokens": 0.0011716437769675435, "Total Count of PDF token": 794, "name": "0.0%"}, {"pdf_letters": " ", "ocr_letters": "Z", "% of all OCR tokens": 0.001031459697859336, "Total Count of PDF token": 699, "name": "0.0%"}, {"pdf_letters": " ", "ocr_letters": ";", "% of all OCR tokens": 0.0015287442732221344, "Total Count of PDF token": 1036, "name": "0.0%"}, {"pdf_letters": " ", "ocr_letters": "\u03b5", "% of all OCR tokens": 0.00022429452657313171, "Total Count of PDF token": 152, "name": "0.0%"}, {"pdf_letters": " ", "ocr_letters": "<", "% of all OCR tokens": 0.0014667681540374534, "Total Count of PDF token": 994, "name": "0.0%"}, {"pdf_letters": " ", "ocr_letters": "b", "% of all OCR tokens": 0.0034500039679472494, "Total Count of PDF token": 2338, "name": "0.0%"}, {"pdf_letters": " ", "ocr_letters": "\u03c3", "% of all OCR tokens": 0.0005710656696302762, "Total Count of PDF token": 387, "name": "0.0%"}, {"pdf_letters": " ", "ocr_letters": "\u220e", "% of all OCR tokens": 0.000348246764942494, "Total Count of PDF token": 236, "name": "0.0%"}, {"pdf_letters": " ", "ocr_letters": "\u2220", "% of all OCR tokens": 0.00048400397839465267, "Total Count of PDF token": 328, "name": "0.0%"}, {"pdf_letters": " ", "ocr_letters": "\u2271", "% of all OCR tokens": 0.00026561193936291917, "Total Count of PDF token": 180, "name": "0.0%"}, {"pdf_letters": " ", "ocr_letters": "B", "% of all OCR tokens": 0.0025572527273107714, "Total Count of PDF token": 1733, "name": "0.0%"}, {"pdf_letters": " ", "ocr_letters": "\u00ab", "% of all OCR tokens": 0.0013147790998464498, "Total Count of PDF token": 891, "name": "0.0%"}, {"pdf_letters": " ", "ocr_letters": "\u22ef", "% of all OCR tokens": 0.0029940368053742385, "Total Count of PDF token": 2029, "name": "0.0%"}, {"pdf_letters": " ", "ocr_letters": "q", "% of all OCR tokens": 0.0008691412904708854, "Total Count of PDF token": 589, "name": "0.0%"}, {"pdf_letters": " ", "ocr_letters": "|", "% of all OCR tokens": 0.008143957185244171, "Total Count of PDF token": 5519, "name": "0.01%"}, {"pdf_letters": " ", "ocr_letters": "N", "% of all OCR tokens": 0.002577911433705665, "Total Count of PDF token": 1747, "name": "0.0%"}, {"pdf_letters": " ", "ocr_letters": "\u03bf", "% of all OCR tokens": 0.0026059482495273067, "Total Count of PDF token": 1766, "name": "0.0%"}, {"pdf_letters": " ", "ocr_letters": "!", "% of all OCR tokens": 0.001527268651336785, "Total Count of PDF token": 1035, "name": "0.0%"}, {"pdf_letters": " ", "ocr_letters": "J", "% of all OCR tokens": 0.001339864671897392, "Total Count of PDF token": 908, "name": "0.0%"}, {"pdf_letters": " ", "ocr_letters": "R", "% of all OCR tokens": 0.001658598999132895, "Total Count of PDF token": 1124, "name": "0.0%"}, {"pdf_letters": " ", "ocr_letters": "]", "% of all OCR tokens": 0.0038498974988769776, "Total Count of PDF token": 2609, "name": "0.0%"}, {"pdf_letters": " ", "ocr_letters": "\u00c0", "% of all OCR tokens": 0.0004338328342927679, "Total Count of PDF token": 294, "name": "0.0%"}, {"pdf_letters": " ", "ocr_letters": "\u0399", "% of all OCR tokens": 0.00025970945182152096, "Total Count of PDF token": 176, "name": "0.0%"}, {"pdf_letters": " ", "ocr_letters": "&", "% of all OCR tokens": 0.0007009203955410366, "Total Count of PDF token": 475, "name": "0.0%"}, {"pdf_letters": " ", "ocr_letters": "\u0391", "% of all OCR tokens": 0.00032906368043294983, "Total Count of PDF token": 223, "name": "0.0%"}, {"pdf_letters": " ", "ocr_letters": "=", "% of all OCR tokens": 0.0009075074594899737, "Total Count of PDF token": 615, "name": "0.0%"}, {"pdf_letters": " ", "ocr_letters": "h", "% of all OCR tokens": 0.005082041773143853, "Total Count of PDF token": 3444, "name": "0.01%"}, {"pdf_letters": " ", "ocr_letters": "f", "% of all OCR tokens": 0.004938906450264946, "Total Count of PDF token": 3347, "name": "0.0%"}, {"pdf_letters": " ", "ocr_letters": "[", "% of all OCR tokens": 0.0021234198930180034, "Total Count of PDF token": 1439, "name": "0.0%"}, {"pdf_letters": " ", "ocr_letters": "\u2191", "% of all OCR tokens": 0.003470662674342143, "Total Count of PDF token": 2352, "name": "0.0%"}, {"pdf_letters": " ", "ocr_letters": "\u2236", "% of all OCR tokens": 0.0014697193978081525, "Total Count of PDF token": 996, "name": "0.0%"}, {"pdf_letters": " ", "ocr_letters": "\u2294", "% of all OCR tokens": 0.0033585154110555774, "Total Count of PDF token": 2276, "name": "0.0%"}, {"pdf_letters": " ", "ocr_letters": "'", "% of all OCR tokens": 0.0017486119341392178, "Total Count of PDF token": 1185, "name": "0.0%"}, {"pdf_letters": " ", "ocr_letters": "\u21b2", "% of all OCR tokens": 0.0022458965095020164, "Total Count of PDF token": 1522, "name": "0.0%"}, {"pdf_letters": " ", "ocr_letters": "\u2194", "% of all OCR tokens": 0.00024052636731197678, "Total Count of PDF token": 163, "name": "0.0%"}, {"pdf_letters": " ", "ocr_letters": "\u22bd", "% of all OCR tokens": 0.0016349890489673023, "Total Count of PDF token": 1108, "name": "0.0%"}, {"pdf_letters": " ", "ocr_letters": "\u21a7", "% of all OCR tokens": 0.0038617024739597745, "Total Count of PDF token": 2617, "name": "0.0%"}, {"pdf_letters": " ", "ocr_letters": "\u2278", "% of all OCR tokens": 0.0001859283575540434, "Total Count of PDF token": 126, "name": "0.0%"}, {"pdf_letters": " ", "ocr_letters": "\u22b2", "% of all OCR tokens": 0.00045154029691696254, "Total Count of PDF token": 306, "name": "0.0%"}, {"pdf_letters": " ", "ocr_letters": "\u2240", "% of all OCR tokens": 0.0011406557173752026, "Total Count of PDF token": 773, "name": "0.0%"}, {"pdf_letters": " ", "ocr_letters": "\u2198", "% of all OCR tokens": 0.000305453730267357, "Total Count of PDF token": 207, "name": "0.0%"}, {"pdf_letters": " ", "ocr_letters": "\u03a4", "% of all OCR tokens": 0.0003452955211717949, "Total Count of PDF token": 234, "name": "0.0%"}, {"pdf_letters": " ", "ocr_letters": "{", "% of all OCR tokens": 0.0004913820878214004, "Total Count of PDF token": 333, "name": "0.0%"}, {"pdf_letters": " ", "ocr_letters": "\u22df", "% of all OCR tokens": 0.0011804975082796406, "Total Count of PDF token": 800, "name": "0.0%"}, {"pdf_letters": " ", "ocr_letters": "\u22c0", "% of all OCR tokens": 0.00015198905419100373, "Total Count of PDF token": 103, "name": "0.0%"}, {"pdf_letters": " ", "ocr_letters": "\u039f", "% of all OCR tokens": 0.00048400397839465267, "Total Count of PDF token": 328, "name": "0.0%"}, {"pdf_letters": " ", "ocr_letters": "\u22e1", "% of all OCR tokens": 0.00047810149085325445, "Total Count of PDF token": 324, "name": "0.0%"}, {"pdf_letters": " ", "ocr_letters": "\u201d", "% of all OCR tokens": 0.000798311439974107, "Total Count of PDF token": 541, "name": "0.0%"}, {"pdf_letters": " ", "ocr_letters": "$", "% of all OCR tokens": 0.0004249791029806707, "Total Count of PDF token": 288, "name": "0.0%"}, {"pdf_letters": " ", "ocr_letters": "\u03b9", "% of all OCR tokens": 0.0006935422861142888, "Total Count of PDF token": 470, "name": "0.0%"}, {"pdf_letters": " ", "ocr_letters": "\u21b5", "% of all OCR tokens": 0.0011126189015535613, "Total Count of PDF token": 754, "name": "0.0%"}, {"pdf_letters": " ", "ocr_letters": "\u227a", "% of all OCR tokens": 0.002998463671030287, "Total Count of PDF token": 2032, "name": "0.0%"}, {"pdf_letters": " ", "ocr_letters": "\u2197", "% of all OCR tokens": 0.0001829771137833443, "Total Count of PDF token": 124, "name": "0.0%"}, {"pdf_letters": " ", "ocr_letters": "\u22dd", "% of all OCR tokens": 0.0010137522352351414, "Total Count of PDF token": 687, "name": "0.0%"}, {"pdf_letters": " ", "ocr_letters": "\u2211", "% of all OCR tokens": 0.0002847950238724633, "Total Count of PDF token": 193, "name": "0.0%"}, {"pdf_letters": " ", "ocr_letters": "\u21a9", "% of all OCR tokens": 0.00021544079526103442, "Total Count of PDF token": 146, "name": "0.0%"}, {"pdf_letters": " ", "ocr_letters": "\u22c3", "% of all OCR tokens": 0.00037923482453483456, "Total Count of PDF token": 257, "name": "0.0%"}, {"pdf_letters": " ", "ocr_letters": "\u221f", "% of all OCR tokens": 0.00018445273566869384, "Total Count of PDF token": 125, "name": "0.0%"}, {"pdf_letters": " ", "ocr_letters": "\u22d6", "% of all OCR tokens": 0.000942922384738363, "Total Count of PDF token": 639, "name": "0.0%"}, {"pdf_letters": " ", "ocr_letters": "\u2293", "% of all OCR tokens": 0.0007865064648913105, "Total Count of PDF token": 533, "name": "0.0%"}, {"pdf_letters": " ", "ocr_letters": "\u21b1", "% of all OCR tokens": 0.0001534646760763533, "Total Count of PDF token": 104, "name": "0.0%"}, {"pdf_letters": " ", "ocr_letters": "\u21bf", "% of all OCR tokens": 0.0007230547238212798, "Total Count of PDF token": 490, "name": "0.0%"}, {"pdf_letters": " ", "ocr_letters": "\u03c4", "% of all OCR tokens": 0.0006050049729933158, "Total Count of PDF token": 410, "name": "0.0%"}, {"pdf_letters": " ", "ocr_letters": "\u21c1", "% of all OCR tokens": 0.0016526965115914968, "Total Count of PDF token": 1120, "name": "0.0%"}, {"pdf_letters": " ", "ocr_letters": "\u2223", "% of all OCR tokens": 0.0020555412862919243, "Total Count of PDF token": 1393, "name": "0.0%"}, {"pdf_letters": " ", "ocr_letters": "\u2199", "% of all OCR tokens": 0.0003128318396941048, "Total Count of PDF token": 212, "name": "0.0%"}, {"pdf_letters": " ", "ocr_letters": "\u2215", "% of all OCR tokens": 0.0005548338288914311, "Total Count of PDF token": 376, "name": "0.0%"}, {"pdf_letters": " ", "ocr_letters": "\u21bb", "% of all OCR tokens": 0.0004928577097067499, "Total Count of PDF token": 334, "name": "0.0%"}, {"pdf_letters": " ", "ocr_letters": "\u2018", "% of all OCR tokens": 0.0013988895473113741, "Total Count of PDF token": 948, "name": "0.0%"}, {"pdf_letters": " ", "ocr_letters": "\u03c9", "% of all OCR tokens": 0.00018445273566869384, "Total Count of PDF token": 125, "name": "0.0%"}, {"pdf_letters": " ", "ocr_letters": "\u20ac", "% of all OCR tokens": 0.0004677721376558076, "Total Count of PDF token": 317, "name": "0.0%"}, {"pdf_letters": " ", "ocr_letters": "\u225f", "% of all OCR tokens": 0.0004471134312609139, "Total Count of PDF token": 303, "name": "0.0%"}, {"pdf_letters": " ", "ocr_letters": "\u03c1", "% of all OCR tokens": 0.00019183084509544158, "Total Count of PDF token": 130, "name": "0.0%"}, {"pdf_letters": " ", "ocr_letters": "\u03bc", "% of all OCR tokens": 0.0007997870618594565, "Total Count of PDF token": 542, "name": "0.0%"}, {"pdf_letters": " ", "ocr_letters": "\u2019", "% of all OCR tokens": 0.000742237808330824, "Total Count of PDF token": 503, "name": "0.0%"}, {"pdf_letters": " ", "ocr_letters": "\u03b7", "% of all OCR tokens": 0.00017855024812729565, "Total Count of PDF token": 121, "name": "0.0%"}, {"pdf_letters": " ", "ocr_letters": "\u201c", "% of all OCR tokens": 0.0009089830813753232, "Total Count of PDF token": 616, "name": "0.0%"}, {"pdf_letters": " ", "ocr_letters": "%", "% of all OCR tokens": 0.0006330417888149572, "Total Count of PDF token": 429, "name": "0.0%"}, {"pdf_letters": " ", "ocr_letters": "\u00a2", "% of all OCR tokens": 0.0002375751235412777, "Total Count of PDF token": 161, "name": "0.0%"}, {"pdf_letters": " ", "ocr_letters": "\u2212", "% of all OCR tokens": 0.0005887731322544707, "Total Count of PDF token": 399, "name": "0.0%"}, {"pdf_letters": " ", "ocr_letters": "\u22ee", "% of all OCR tokens": 0.00029807562084060925, "Total Count of PDF token": 202, "name": "0.0%"}, {"pdf_letters": " ", "ocr_letters": "\u03b4", "% of all OCR tokens": 0.00019330646698079116, "Total Count of PDF token": 131, "name": "0.0%"}, {"pdf_letters": " ", "ocr_letters": "\u22cf", "% of all OCR tokens": 0.00020216019829288849, "Total Count of PDF token": 137, "name": "0.0%"}, {"pdf_letters": " ", "ocr_letters": "\u22a5", "% of all OCR tokens": 0.00015494029796170284, "Total Count of PDF token": 105, "name": "0.0%"}, {"pdf_letters": " ", "ocr_letters": "\u2201", "% of all OCR tokens": 0.00016379402927380014, "Total Count of PDF token": 111, "name": "0.0%"}, {"pdf_letters": " ", "ocr_letters": "\u22ba", "% of all OCR tokens": 0.00021396517337568486, "Total Count of PDF token": 145, "name": "0.0%"}, {"pdf_letters": " ", "ocr_letters": "\u21be", "% of all OCR tokens": 0.0002065870639489371, "Total Count of PDF token": 140, "name": "0.0%"}, {"pdf_letters": " ", "ocr_letters": "\u03c2", "% of all OCR tokens": 0.0003202099491208525, "Total Count of PDF token": 217, "name": "0.0%"}, {"pdf_letters": " ", "ocr_letters": "\u00f3", "% of all OCR tokens": 0.0001534646760763533, "Total Count of PDF token": 104, "name": "0.0%"}, {"pdf_letters": " ", "ocr_letters": "\u0397", "% of all OCR tokens": 0.0003452955211717949, "Total Count of PDF token": 234, "name": "0.0%"}, {"pdf_letters": " ", "ocr_letters": "}", "% of all OCR tokens": 0.00017117213870054788, "Total Count of PDF token": 116, "name": "0.0%"}, {"pdf_letters": " ", "ocr_letters": "\u2225", "% of all OCR tokens": 0.00014903781042030463, "Total Count of PDF token": 101, "name": "0.0%"}, {"pdf_letters": " ", "ocr_letters": "\u22b0", "% of all OCR tokens": 0.00015198905419100373, "Total Count of PDF token": 103, "name": "0.0%"}, {"pdf_letters": " ", "ocr_letters": "\u0395", "% of all OCR tokens": 0.00035267363059854264, "Total Count of PDF token": 239, "name": "0.0%"}, {"pdf_letters": " ", "ocr_letters": "\u2122", "% of all OCR tokens": 0.0002095383077196362, "Total Count of PDF token": 142, "name": "0.0%"}, {"pdf_letters": " ", "ocr_letters": "\u2280", "% of all OCR tokens": 0.00016379402927380014, "Total Count of PDF token": 111, "name": "0.0%"}, {"pdf_letters": " ", "ocr_letters": "\u22c1", "% of all OCR tokens": 0.00016379402927380014, "Total Count of PDF token": 111, "name": "0.0%"}, {"pdf_letters": " ", "ocr_letters": "\u21c0", "% of all OCR tokens": 0.0003202099491208525, "Total Count of PDF token": 217, "name": "0.0%"}, {"pdf_letters": " ", "ocr_letters": "\u226f", "% of all OCR tokens": 0.00032168557100620206, "Total Count of PDF token": 218, "name": "0.0%"}, {"pdf_letters": " ", "ocr_letters": "\u222b", "% of all OCR tokens": 0.00025085572050942363, "Total Count of PDF token": 170, "name": "0.0%"}, {"pdf_letters": " ", "ocr_letters": "\u00e9", "% of all OCR tokens": 0.00023167263599987948, "Total Count of PDF token": 157, "name": "0.0%"}, {"pdf_letters": "'\\\\xa0'", "ocr_letters": "1", "% of all OCR tokens": 2.1081401623887603, "Total Count of PDF token": 10274, "name": "2.11%"}, {"pdf_letters": "'\\\\xa0'", "ocr_letters": "INSERT", "% of all OCR tokens": 74.5892573904943, "Total Count of PDF token": 363510, "name": "74.59%"}, {"pdf_letters": "'\\\\xa0'", "ocr_letters": "4", "% of all OCR tokens": 0.9972319631311443, "Total Count of PDF token": 4860, "name": "1.0%"}, {"pdf_letters": "'\\\\xa0'", "ocr_letters": "3", "% of all OCR tokens": 1.339081438558405, "Total Count of PDF token": 6526, "name": "1.34%"}, {"pdf_letters": "'\\\\xa0'", "ocr_letters": " ", "% of all OCR tokens": 4.354784764101291, "Total Count of PDF token": 21223, "name": "4.35%"}, {"pdf_letters": "'\\\\xa0'", "ocr_letters": "|", "% of all OCR tokens": 0.31476416284838993, "Total Count of PDF token": 1534, "name": "0.31%"}, {"pdf_letters": "'\\\\xa0'", "ocr_letters": "9", "% of all OCR tokens": 0.2622350717863379, "Total Count of PDF token": 1278, "name": "0.26%"}, {"pdf_letters": "'\\\\xa0'", "ocr_letters": "u", "% of all OCR tokens": 0.19739447500661741, "Total Count of PDF token": 962, "name": "0.2%"}, {"pdf_letters": "'\\\\xa0'", "ocr_letters": "0", "% of all OCR tokens": 0.24828203197298035, "Total Count of PDF token": 1210, "name": "0.25%"}, {"pdf_letters": "'\\\\xa0'", "ocr_letters": "8", "% of all OCR tokens": 0.3139433958005454, "Total Count of PDF token": 1530, "name": "0.31%"}, {"pdf_letters": "'\\\\xa0'", "ocr_letters": ".", "% of all OCR tokens": 1.3314893433658426, "Total Count of PDF token": 6489, "name": "1.33%"}, {"pdf_letters": "'\\\\xa0'", "ocr_letters": "p", "% of all OCR tokens": 0.0759209519256221, "Total Count of PDF token": 370, "name": "0.08%"}, {"pdf_letters": "'\\\\xa0'", "ocr_letters": "O", "% of all OCR tokens": 0.30450457475033293, "Total Count of PDF token": 1484, "name": "0.3%"}, {"pdf_letters": "'\\\\xa0'", "ocr_letters": "D", "% of all OCR tokens": 0.34697926947628904, "Total Count of PDF token": 1691, "name": "0.35%"}, {"pdf_letters": "'\\\\xa0'", "ocr_letters": "S", "% of all OCR tokens": 0.2353549509694285, "Total Count of PDF token": 1147, "name": "0.24%"}, {"pdf_letters": "'\\\\xa0'", "ocr_letters": "2", "% of all OCR tokens": 1.6230668371126238, "Total Count of PDF token": 7910, "name": "1.62%"}, {"pdf_letters": "'\\\\xa0'", "ocr_letters": "L", "% of all OCR tokens": 0.4715306689867015, "Total Count of PDF token": 2298, "name": "0.47%"}, {"pdf_letters": "'\\\\xa0'", "ocr_letters": "K", "% of all OCR tokens": 0.0211347514819975, "Total Count of PDF token": 103, "name": "0.02%"}, {"pdf_letters": "'\\\\xa0'", "ocr_letters": "k", "% of all OCR tokens": 0.18795565395640496, "Total Count of PDF token": 916, "name": "0.19%"}, {"pdf_letters": "'\\\\xa0'", "ocr_letters": "5", "% of all OCR tokens": 0.9217213947294445, "Total Count of PDF token": 4492, "name": "0.92%"}, {"pdf_letters": "'\\\\xa0'", "ocr_letters": "s", "% of all OCR tokens": 0.14773806861202138, "Total Count of PDF token": 720, "name": "0.15%"}, {"pdf_letters": "'\\\\xa0'", "ocr_letters": "m", "% of all OCR tokens": 0.0679184732091376, "Total Count of PDF token": 331, "name": "0.07%"}, {"pdf_letters": "'\\\\xa0'", "ocr_letters": "l", "% of all OCR tokens": 0.25238586721220313, "Total Count of PDF token": 1230, "name": "0.25%"}, {"pdf_letters": "'\\\\xa0'", "ocr_letters": "A", "% of all OCR tokens": 0.7573627933985706, "Total Count of PDF token": 3691, "name": "0.76%"}, {"pdf_letters": "'\\\\xa0'", "ocr_letters": "i", "% of all OCR tokens": 0.19801005029250088, "Total Count of PDF token": 965, "name": "0.2%"}, {"pdf_letters": "'\\\\xa0'", "ocr_letters": "\u20ac", "% of all OCR tokens": 0.1715403129995137, "Total Count of PDF token": 836, "name": "0.17%"}, {"pdf_letters": "'\\\\xa0'", "ocr_letters": "\u03bf", "% of all OCR tokens": 0.15902361551988412, "Total Count of PDF token": 775, "name": "0.16%"}, {"pdf_letters": "'\\\\xa0'", "ocr_letters": "n", "% of all OCR tokens": 0.3806307184379161, "Total Count of PDF token": 1855, "name": "0.38%"}, {"pdf_letters": "'\\\\xa0'", "ocr_letters": "o", "% of all OCR tokens": 0.1608703413775344, "Total Count of PDF token": 784, "name": "0.16%"}, {"pdf_letters": "'\\\\xa0'", "ocr_letters": ")", "% of all OCR tokens": 0.07386903430601069, "Total Count of PDF token": 360, "name": "0.07%"}, {"pdf_letters": "'\\\\xa0'", "ocr_letters": "X", "% of all OCR tokens": 0.044936995869489835, "Total Count of PDF token": 219, "name": "0.04%"}, {"pdf_letters": "'\\\\xa0'", "ocr_letters": "\u039c", "% of all OCR tokens": 0.024828203197298036, "Total Count of PDF token": 121, "name": "0.02%"}, {"pdf_letters": "'\\\\xa0'", "ocr_letters": "&", "% of all OCR tokens": 0.04267988648791728, "Total Count of PDF token": 208, "name": "0.04%"}, {"pdf_letters": "'\\\\xa0'", "ocr_letters": "v", "% of all OCR tokens": 0.08966879997701852, "Total Count of PDF token": 437, "name": "0.09%"}, {"pdf_letters": "'\\\\xa0'", "ocr_letters": "I", "% of all OCR tokens": 1.0598154505292923, "Total Count of PDF token": 5165, "name": "1.06%"}, {"pdf_letters": "'\\\\xa0'", "ocr_letters": "7", "% of all OCR tokens": 0.43213385069016247, "Total Count of PDF token": 2106, "name": "0.43%"}, {"pdf_letters": "'\\\\xa0'", "ocr_letters": "\u00a3", "% of all OCR tokens": 0.025854162007103738, "Total Count of PDF token": 126, "name": "0.03%"}, {"pdf_letters": "'\\\\xa0'", "ocr_letters": "C", "% of all OCR tokens": 0.5035405838526394, "Total Count of PDF token": 2454, "name": "0.5%"}, {"pdf_letters": "'\\\\xa0'", "ocr_letters": "\"", "% of all OCR tokens": 0.05088755696636292, "Total Count of PDF token": 248, "name": "0.05%"}, {"pdf_letters": "'\\\\xa0'", "ocr_letters": "H", "% of all OCR tokens": 0.10074915512292013, "Total Count of PDF token": 491, "name": "0.1%"}, {"pdf_letters": "'\\\\xa0'", "ocr_letters": "(", "% of all OCR tokens": 0.16517936837871833, "Total Count of PDF token": 805, "name": "0.17%"}, {"pdf_letters": "'\\\\xa0'", "ocr_letters": "T", "% of all OCR tokens": 0.18405701047914327, "Total Count of PDF token": 897, "name": "0.18%"}, {"pdf_letters": "'\\\\xa0'", "ocr_letters": "?", "% of all OCR tokens": 0.09048956702486309, "Total Count of PDF token": 441, "name": "0.09%"}, {"pdf_letters": "'\\\\xa0'", "ocr_letters": "c", "% of all OCR tokens": 0.07263788373424385, "Total Count of PDF token": 354, "name": "0.07%"}, {"pdf_letters": "'\\\\xa0'", "ocr_letters": ";", "% of all OCR tokens": 0.021545135005919782, "Total Count of PDF token": 105, "name": "0.02%"}, {"pdf_letters": "'\\\\xa0'", "ocr_letters": "\u22c5", "% of all OCR tokens": 0.022160710291803207, "Total Count of PDF token": 108, "name": "0.02%"}, {"pdf_letters": "'\\\\xa0'", "ocr_letters": "+", "% of all OCR tokens": 0.07427941782993297, "Total Count of PDF token": 362, "name": "0.07%"}, {"pdf_letters": "'\\\\xa0'", "ocr_letters": "6", "% of all OCR tokens": 0.5628410030594092, "Total Count of PDF token": 2743, "name": "0.56%"}, {"pdf_letters": "'\\\\xa0'", "ocr_letters": "w", "% of all OCR tokens": 0.030163189008287693, "Total Count of PDF token": 147, "name": "0.03%"}, {"pdf_letters": "'\\\\xa0'", "ocr_letters": "[", "% of all OCR tokens": 0.15450939675673903, "Total Count of PDF token": 753, "name": "0.15%"}, {"pdf_letters": "'\\\\xa0'", "ocr_letters": "e", "% of all OCR tokens": 0.4949225298502715, "Total Count of PDF token": 2412, "name": "0.49%"}, {"pdf_letters": "'\\\\xa0'", "ocr_letters": "a", "% of all OCR tokens": 0.11983198898530621, "Total Count of PDF token": 584, "name": "0.12%"}, {"pdf_letters": "'\\\\xa0'", "ocr_letters": "M", "% of all OCR tokens": 0.14158231575318714, "Total Count of PDF token": 690, "name": "0.14%"}, {"pdf_letters": "'\\\\xa0'", "ocr_letters": "/", "% of all OCR tokens": 0.02523858672122032, "Total Count of PDF token": 123, "name": "0.03%"}, {"pdf_letters": "'\\\\xa0'", "ocr_letters": ",", "% of all OCR tokens": 0.08761688235740711, "Total Count of PDF token": 427, "name": "0.09%"}, {"pdf_letters": "'\\\\xa0'", "ocr_letters": "R", "% of all OCR tokens": 0.053555049871857746, "Total Count of PDF token": 261, "name": "0.05%"}, {"pdf_letters": "'\\\\xa0'", "ocr_letters": "x", "% of all OCR tokens": 0.05971080273069197, "Total Count of PDF token": 291, "name": "0.06%"}, {"pdf_letters": "'\\\\xa0'", "ocr_letters": "E", "% of all OCR tokens": 0.13953039813357573, "Total Count of PDF token": 680, "name": "0.14%"}, {"pdf_letters": "'\\\\xa0'", "ocr_letters": "g", "% of all OCR tokens": 0.051503132252246335, "Total Count of PDF token": 251, "name": "0.05%"}, {"pdf_letters": "'\\\\xa0'", "ocr_letters": "d", "% of all OCR tokens": 0.04596295467929554, "Total Count of PDF token": 224, "name": "0.05%"}, {"pdf_letters": "'\\\\xa0'", "ocr_letters": "h", "% of all OCR tokens": 0.027085312578870584, "Total Count of PDF token": 132, "name": "0.03%"}, {"pdf_letters": "'\\\\xa0'", "ocr_letters": "r", "% of all OCR tokens": 0.059915994492653106, "Total Count of PDF token": 292, "name": "0.06%"}, {"pdf_letters": "'\\\\xa0'", "ocr_letters": "U", "% of all OCR tokens": 0.027700887864754005, "Total Count of PDF token": 135, "name": "0.03%"}, {"pdf_letters": "'\\\\xa0'", "ocr_letters": "\u03bd", "% of all OCR tokens": 0.030573572532209974, "Total Count of PDF token": 149, "name": "0.03%"}, {"pdf_letters": "'\\\\xa0'", "ocr_letters": "~", "% of all OCR tokens": 0.024828203197298036, "Total Count of PDF token": 121, "name": "0.02%"}, {"pdf_letters": "'\\\\xa0'", "ocr_letters": "-", "% of all OCR tokens": 0.03878124301065561, "Total Count of PDF token": 189, "name": "0.04%"}, {"pdf_letters": "'\\\\xa0'", "ocr_letters": "b", "% of all OCR tokens": 0.022776285577686625, "Total Count of PDF token": 111, "name": "0.02%"}, {"pdf_letters": "'\\\\xa0'", "ocr_letters": "t", "% of all OCR tokens": 0.07961440364092262, "Total Count of PDF token": 388, "name": "0.08%"}, {"pdf_letters": "'\\\\xa0'", "ocr_letters": "\u03c2", "% of all OCR tokens": 0.05642773453931371, "Total Count of PDF token": 275, "name": "0.06%"}, {"pdf_letters": "'\\\\xa0'", "ocr_letters": "\u03b1", "% of all OCR tokens": 0.025648970245142594, "Total Count of PDF token": 125, "name": "0.03%"}, {"pdf_letters": "'\\\\xa0'", "ocr_letters": "W", "% of all OCR tokens": 0.035498174819277355, "Total Count of PDF token": 173, "name": "0.04%"}, {"pdf_letters": "'\\\\xa0'", "ocr_letters": "\u2014", "% of all OCR tokens": 0.08146112949857288, "Total Count of PDF token": 397, "name": "0.08%"}, {"pdf_letters": "'\\\\xa0'", "ocr_letters": ":", "% of all OCR tokens": 0.06607174735148734, "Total Count of PDF token": 322, "name": "0.07%"}, {"pdf_letters": "'\\\\xa0'", "ocr_letters": "\u039f", "% of all OCR tokens": 0.08064036245072832, "Total Count of PDF token": 393, "name": "0.08%"}, {"pdf_letters": "'\\\\xa0'", "ocr_letters": "{", "% of all OCR tokens": 0.024212627911414614, "Total Count of PDF token": 118, "name": "0.02%"}, {"pdf_letters": "'\\\\xa0'", "ocr_letters": "!", "% of all OCR tokens": 0.12947600179747984, "Total Count of PDF token": 631, "name": "0.13%"}, {"pdf_letters": "'\\\\xa0'", "ocr_letters": "P", "% of all OCR tokens": 0.04863044758479037, "Total Count of PDF token": 237, "name": "0.05%"}, {"pdf_letters": "'\\\\xa0'", "ocr_letters": "\u00c0", "% of all OCR tokens": 0.07243269197228269, "Total Count of PDF token": 353, "name": "0.07%"}, {"pdf_letters": "'\\\\xa0'", "ocr_letters": "B", "% of all OCR tokens": 0.0911051423107465, "Total Count of PDF token": 444, "name": "0.09%"}, {"pdf_letters": "'\\\\xa0'", "ocr_letters": "V", "% of all OCR tokens": 0.030573572532209974, "Total Count of PDF token": 149, "name": "0.03%"}, {"pdf_letters": "'\\\\xa0'", "ocr_letters": "j", "% of all OCR tokens": 0.11408661965039428, "Total Count of PDF token": 556, "name": "0.11%"}, {"pdf_letters": "'\\\\xa0'", "ocr_letters": "J", "% of all OCR tokens": 0.022365902053764347, "Total Count of PDF token": 109, "name": "0.02%"}, {"pdf_letters": "'\\\\xa0'", "ocr_letters": "y", "% of all OCR tokens": 0.09192590935859107, "Total Count of PDF token": 448, "name": "0.09%"}, {"pdf_letters": "'\\\\xa0'", "ocr_letters": "\u00ab", "% of all OCR tokens": 0.021955518529842063, "Total Count of PDF token": 107, "name": "0.02%"}, {"pdf_letters": "'\\\\xa0'", "ocr_letters": "N", "% of all OCR tokens": 0.1348109876084695, "Total Count of PDF token": 657, "name": "0.13%"}, {"pdf_letters": "'\\\\xa0'", "ocr_letters": "f", "% of all OCR tokens": 0.041448735916150434, "Total Count of PDF token": 202, "name": "0.04%"}, {"pdf_letters": "'\\\\xa0'", "ocr_letters": "=", "% of all OCR tokens": 0.030368380770248834, "Total Count of PDF token": 148, "name": "0.03%"}, {"pdf_letters": "'\\\\xa0'", "ocr_letters": "]", "% of all OCR tokens": 0.08577015649975685, "Total Count of PDF token": 418, "name": "0.09%"}, {"pdf_letters": "'\\\\xa0'", "ocr_letters": "\u03a0", "% of all OCR tokens": 0.029342421960443135, "Total Count of PDF token": 143, "name": "0.03%"}, {"pdf_letters": "'\\\\xa0'", "ocr_letters": "F", "% of all OCR tokens": 0.03796047596281105, "Total Count of PDF token": 185, "name": "0.04%"}, {"pdf_letters": "'\\\\xa0'", "ocr_letters": "G", "% of all OCR tokens": 0.03447221600947165, "Total Count of PDF token": 168, "name": "0.03%"}, {"pdf_letters": "\u2013", "ocr_letters": "INSERT", "% of all OCR tokens": 47.26635981588954, "Total Count of PDF token": 47238, "name": "47.27%"}, {"pdf_letters": "\u2013", "ocr_letters": ".", "% of all OCR tokens": 6.936161697018211, "Total Count of PDF token": 6932, "name": "6.94%"}, {"pdf_letters": "\u2013", "ocr_letters": " ", "% of all OCR tokens": 1.7810686411847108, "Total Count of PDF token": 1780, "name": "1.78%"}, {"pdf_letters": "\u2013", "ocr_letters": "-", "% of all OCR tokens": 19.418651190714428, "Total Count of PDF token": 19407, "name": "19.42%"}, {"pdf_letters": "\u2013", "ocr_letters": "\u2014", "% of all OCR tokens": 12.346407844706823, "Total Count of PDF token": 12339, "name": "12.35%"}, {"pdf_letters": "\u2013", "ocr_letters": "o", "% of all OCR tokens": 0.23514108465079045, "Total Count of PDF token": 235, "name": "0.24%"}, {"pdf_letters": "\u2013", "ocr_letters": "A", "% of all OCR tokens": 0.22513508104862917, "Total Count of PDF token": 225, "name": "0.23%"}, {"pdf_letters": "\u2013", "ocr_letters": "E", "% of all OCR tokens": 0.13207924754852912, "Total Count of PDF token": 132, "name": "0.13%"}, {"pdf_letters": "\u2013", "ocr_letters": "e", "% of all OCR tokens": 0.2121272763658195, "Total Count of PDF token": 212, "name": "0.21%"}, {"pdf_letters": "\u2013", "ocr_letters": "2", "% of all OCR tokens": 0.6834100460276166, "Total Count of PDF token": 683, "name": "0.68%"}, {"pdf_letters": "\u2013", "ocr_letters": "S", "% of all OCR tokens": 0.208124874924955, "Total Count of PDF token": 208, "name": "0.21%"}, {"pdf_letters": "\u2013", "ocr_letters": "1", "% of all OCR tokens": 1.273764258555133, "Total Count of PDF token": 1273, "name": "1.27%"}, {"pdf_letters": "\u2013", "ocr_letters": "5", "% of all OCR tokens": 0.3682209325595357, "Total Count of PDF token": 368, "name": "0.37%"}, {"pdf_letters": "\u2013", "ocr_letters": "0", "% of all OCR tokens": 0.5683410046027616, "Total Count of PDF token": 568, "name": "0.57%"}, {"pdf_letters": "\u2013", "ocr_letters": "4", "% of all OCR tokens": 0.1751050630378227, "Total Count of PDF token": 175, "name": "0.18%"}, {"pdf_letters": "\u2013", "ocr_letters": "O", "% of all OCR tokens": 0.43826295777466484, "Total Count of PDF token": 438, "name": "0.44%"}, {"pdf_letters": "\u2013", "ocr_letters": "(", "% of all OCR tokens": 0.16910146087652592, "Total Count of PDF token": 169, "name": "0.17%"}, {"pdf_letters": "\u2013", "ocr_letters": "3", "% of all OCR tokens": 0.31018611166700016, "Total Count of PDF token": 310, "name": "0.31%"}, {"pdf_letters": "\u2013", "ocr_letters": "9", "% of all OCR tokens": 0.1110666399839904, "Total Count of PDF token": 111, "name": "0.11%"}, {"pdf_letters": "\u2013", "ocr_letters": "I", "% of all OCR tokens": 0.3281969181508905, "Total Count of PDF token": 328, "name": "0.33%"}, {"pdf_letters": "\u2013", "ocr_letters": "u", "% of all OCR tokens": 0.1751050630378227, "Total Count of PDF token": 175, "name": "0.18%"}, {"pdf_letters": "\u2013", "ocr_letters": "L", "% of all OCR tokens": 0.4922953772263358, "Total Count of PDF token": 492, "name": "0.49%"}, {"pdf_letters": "\u2013", "ocr_letters": "\u03bf", "% of all OCR tokens": 0.17610566339803882, "Total Count of PDF token": 176, "name": "0.18%"}, {"pdf_letters": "\u2013", "ocr_letters": "7", "% of all OCR tokens": 0.2021212727636582, "Total Count of PDF token": 202, "name": "0.2%"}, {"pdf_letters": "\u2013", "ocr_letters": "s", "% of all OCR tokens": 0.11506904142485491, "Total Count of PDF token": 115, "name": "0.12%"}, {"pdf_letters": "\u2013", "ocr_letters": "/", "% of all OCR tokens": 0.12307384430658395, "Total Count of PDF token": 123, "name": "0.12%"}, {"pdf_letters": "\u2013", "ocr_letters": "6", "% of all OCR tokens": 0.12007204322593557, "Total Count of PDF token": 120, "name": "0.12%"}, {"pdf_letters": "\u2013", "ocr_letters": ":", "% of all OCR tokens": 0.1891134680808485, "Total Count of PDF token": 189, "name": "0.19%"}, {"pdf_letters": "\u2013", "ocr_letters": "a", "% of all OCR tokens": 0.13408044826896137, "Total Count of PDF token": 134, "name": "0.13%"}, {"pdf_letters": "\u2013", "ocr_letters": "l", "% of all OCR tokens": 0.27116269761857115, "Total Count of PDF token": 271, "name": "0.27%"}, {"pdf_letters": "\u2013", "ocr_letters": "M", "% of all OCR tokens": 0.14408645187112268, "Total Count of PDF token": 144, "name": "0.14%"}, {"pdf_letters": "\u2013", "ocr_letters": "T", "% of all OCR tokens": 0.1681008605163098, "Total Count of PDF token": 168, "name": "0.17%"}, {"pdf_letters": "\u2013", "ocr_letters": "=", "% of all OCR tokens": 0.11907144286571943, "Total Count of PDF token": 119, "name": "0.12%"}, {"pdf_letters": "\u2013", "ocr_letters": "i", "% of all OCR tokens": 0.13908345007004203, "Total Count of PDF token": 139, "name": "0.14%"}, {"pdf_letters": "\u2013", "ocr_letters": "y", "% of all OCR tokens": 0.1040624374624775, "Total Count of PDF token": 104, "name": "0.1%"}, {"pdf_letters": "\u2013", "ocr_letters": ")", "% of all OCR tokens": 0.17710626375825494, "Total Count of PDF token": 177, "name": "0.18%"}, {"pdf_letters": "\u2013", "ocr_letters": "|", "% of all OCR tokens": 0.2111266760056034, "Total Count of PDF token": 211, "name": "0.21%"}, {"pdf_letters": "\u2013", "ocr_letters": "v", "% of all OCR tokens": 0.13408044826896137, "Total Count of PDF token": 134, "name": "0.13%"}, {"pdf_letters": "\u2013", "ocr_letters": "8", "% of all OCR tokens": 0.11206724034420652, "Total Count of PDF token": 112, "name": "0.11%"}, {"pdf_letters": "\u2013", "ocr_letters": "X", "% of all OCR tokens": 0.10506303782269362, "Total Count of PDF token": 105, "name": "0.11%"}, {"pdf_letters": "\u2013", "ocr_letters": "N", "% of all OCR tokens": 0.48128877326395836, "Total Count of PDF token": 481, "name": "0.48%"}, {"pdf_letters": "\u201c", "ocr_letters": "\u201c", "% of all OCR tokens": 43.99635849458617, "Total Count of PDF token": 22714, "name": "44.0%"}, {"pdf_letters": "\u201c", "ocr_letters": "\"", "% of all OCR tokens": 43.7135607337246, "Total Count of PDF token": 22568, "name": "43.71%"}, {"pdf_letters": "\u201c", "ocr_letters": "s", "% of all OCR tokens": 0.2072558932341604, "Total Count of PDF token": 107, "name": "0.21%"}, {"pdf_letters": "\u201c", "ocr_letters": "7", "% of all OCR tokens": 2.6691459895016174, "Total Count of PDF token": 1378, "name": "2.67%"}, {"pdf_letters": "\u201c", "ocr_letters": "INSERT", "% of all OCR tokens": 5.222073721114921, "Total Count of PDF token": 2696, "name": "5.22%"}, {"pdf_letters": "\u201c", "ocr_letters": "~", "% of all OCR tokens": 0.4939275960253356, "Total Count of PDF token": 255, "name": "0.49%"}, {"pdf_letters": "\u201c", "ocr_letters": "c", "% of all OCR tokens": 0.28667170279117515, "Total Count of PDF token": 148, "name": "0.29%"}, {"pdf_letters": "\u201c", "ocr_letters": "v", "% of all OCR tokens": 0.9839812501210607, "Total Count of PDF token": 508, "name": "0.98%"}, {"pdf_letters": "\u201c", "ocr_letters": "U", "% of all OCR tokens": 0.28473473182636994, "Total Count of PDF token": 147, "name": "0.28%"}, {"pdf_letters": "\u201c", "ocr_letters": "*", "% of all OCR tokens": 0.6392004183857284, "Total Count of PDF token": 330, "name": "0.64%"}, {"pdf_letters": "\u201d", "ocr_letters": "\u201d", "% of all OCR tokens": 42.72754697465954, "Total Count of PDF token": 19829, "name": "42.73%"}, {"pdf_letters": "\u201d", "ocr_letters": "\"", "% of all OCR tokens": 23.323564902603, "Total Count of PDF token": 10824, "name": "23.32%"}, {"pdf_letters": "\u201d", "ocr_letters": "INSERT", "% of all OCR tokens": 21.285123254611275, "Total Count of PDF token": 9878, "name": "21.29%"}, {"pdf_letters": "\u201d", "ocr_letters": "7", "% of all OCR tokens": 2.2345285295638684, "Total Count of PDF token": 1037, "name": "2.23%"}, {"pdf_letters": "\u201d", "ocr_letters": "?", "% of all OCR tokens": 1.906998793311498, "Total Count of PDF token": 885, "name": "1.91%"}, {"pdf_letters": "\u201d", "ocr_letters": "\u2122", "% of all OCR tokens": 0.9416479917255645, "Total Count of PDF token": 437, "name": "0.94%"}, {"pdf_letters": "\u201d", "ocr_letters": ".", "% of all OCR tokens": 0.4568177900362007, "Total Count of PDF token": 212, "name": "0.46%"}, {"pdf_letters": "\u201d", "ocr_letters": "v", "% of all OCR tokens": 0.26719531115324946, "Total Count of PDF token": 124, "name": "0.27%"}, {"pdf_letters": "\u201d", "ocr_letters": "\u2019", "% of all OCR tokens": 0.6184278572659886, "Total Count of PDF token": 287, "name": "0.62%"}, {"pdf_letters": "\u201d", "ocr_letters": "\u03bf", "% of all OCR tokens": 0.44819858645061195, "Total Count of PDF token": 208, "name": "0.45%"}, {"pdf_letters": "\u201d", "ocr_letters": "\u00b0", "% of all OCR tokens": 0.2736597138424409, "Total Count of PDF token": 127, "name": "0.27%"}, {"pdf_letters": "\u201d", "ocr_letters": "\u201c", "% of all OCR tokens": 0.4395793828650233, "Total Count of PDF token": 204, "name": "0.44%"}, {"pdf_letters": "\u2014", "ocr_letters": "\u2014", "% of all OCR tokens": 35.67567567567568, "Total Count of PDF token": 3036, "name": "35.68%"}, {"pdf_letters": "\u2014", "ocr_letters": "INSERT", "% of all OCR tokens": 56.13396004700353, "Total Count of PDF token": 4777, "name": "56.13%"}, {"pdf_letters": "\u2014", "ocr_letters": ".", "% of all OCR tokens": 1.8213866039952997, "Total Count of PDF token": 155, "name": "1.82%"}, {"pdf_letters": "\u00e1", "ocr_letters": "a", "% of all OCR tokens": 27.859237536656888, "Total Count of PDF token": 475, "name": "27.86%"}, {"pdf_letters": "\u00e1", "ocr_letters": "\u00e1", "% of all OCR tokens": 65.45454545454545, "Total Count of PDF token": 1116, "name": "65.45%"}, {"pdf_letters": "\u00c5", "ocr_letters": "A", "% of all OCR tokens": 60.4773556160842, "Total Count of PDF token": 13100, "name": "60.48%"}, {"pdf_letters": "\u00c5", "ocr_letters": "X", "% of all OCR tokens": 1.4865426342274133, "Total Count of PDF token": 322, "name": "1.49%"}, {"pdf_letters": "\u00c5", "ocr_letters": "INSERT", "% of all OCR tokens": 11.209085453118508, "Total Count of PDF token": 2428, "name": "11.21%"}, {"pdf_letters": "\u00c5", "ocr_letters": "4", "% of all OCR tokens": 1.2326300724804948, "Total Count of PDF token": 267, "name": "1.23%"}, {"pdf_letters": "\u00c5", "ocr_letters": "\u00c0", "% of all OCR tokens": 14.55611467614607, "Total Count of PDF token": 3153, "name": "14.56%"}, {"pdf_letters": "\u00c5", "ocr_letters": "\u0391", "% of all OCR tokens": 3.997968699506025, "Total Count of PDF token": 866, "name": "4.0%"}, {"pdf_letters": "\u00c5", "ocr_letters": ".", "% of all OCR tokens": 1.3988273856239326, "Total Count of PDF token": 303, "name": "1.4%"}, {"pdf_letters": "\u00c5", "ocr_letters": "\u00c1", "% of all OCR tokens": 0.5863071880337934, "Total Count of PDF token": 127, "name": "0.59%"}, {"pdf_letters": "'\\\\n'", "ocr_letters": "INSERT", "% of all OCR tokens": 99.22913553055926, "Total Count of PDF token": 12615, "name": "99.23%"}, {"pdf_letters": "\u00f1", "ocr_letters": "n", "% of all OCR tokens": 80.46272493573264, "Total Count of PDF token": 313, "name": "80.46%"}, {"pdf_letters": "\u00fc", "ocr_letters": "\u00fc", "% of all OCR tokens": 67.32673267326733, "Total Count of PDF token": 1020, "name": "67.33%"}, {"pdf_letters": "\u00fc", "ocr_letters": "i", "% of all OCR tokens": 17.095709570957098, "Total Count of PDF token": 259, "name": "17.1%"}, {"pdf_letters": "\u2264", "ocr_letters": "<", "% of all OCR tokens": 34.84848484848485, "Total Count of PDF token": 115, "name": "34.85%"}, {"pdf_letters": "\u03bb", "ocr_letters": "A", "% of all OCR tokens": 40.9626216077829, "Total Count of PDF token": 800, "name": "40.96%"}, {"pdf_letters": "\u03bb", "ocr_letters": "INSERT", "% of all OCR tokens": 29.544290834613413, "Total Count of PDF token": 577, "name": "29.54%"}, {"pdf_letters": "\u00e9", "ocr_letters": "\u00e9", "% of all OCR tokens": 94.9993945998305, "Total Count of PDF token": 7846, "name": "95.0%"}, {"pdf_letters": "\u00e9", "ocr_letters": "e", "% of all OCR tokens": 2.409492674657949, "Total Count of PDF token": 199, "name": "2.41%"}, {"pdf_letters": "\u0144", "ocr_letters": "\u00fc", "% of all OCR tokens": 16.09632446134347, "Total Count of PDF token": 127, "name": "16.1%"}, {"pdf_letters": "\u0144", "ocr_letters": "i", "% of all OCR tokens": 25.475285171102662, "Total Count of PDF token": 201, "name": "25.48%"}, {"pdf_letters": "\u0144", "ocr_letters": "n", "% of all OCR tokens": 26.74271229404309, "Total Count of PDF token": 211, "name": "26.74%"}, {"pdf_letters": "\u00b1", "ocr_letters": "INSERT", "% of all OCR tokens": 51.02040816326531, "Total Count of PDF token": 1225, "name": "51.02%"}, {"pdf_letters": "\u00b1", "ocr_letters": "2", "% of all OCR tokens": 5.5810079133694295, "Total Count of PDF token": 134, "name": "5.58%"}, {"pdf_letters": "\u00b1", "ocr_letters": "+", "% of all OCR tokens": 15.993336109954187, "Total Count of PDF token": 384, "name": "15.99%"}, {"pdf_letters": "\u00b1", "ocr_letters": "4", "% of all OCR tokens": 14.577259475218659, "Total Count of PDF token": 350, "name": "14.58%"}, {"pdf_letters": "\u00d6", "ocr_letters": "O", "% of all OCR tokens": 86.95652173913044, "Total Count of PDF token": 120, "name": "86.96%"}, {"pdf_letters": "\u03c7", "ocr_letters": "INSERT", "% of all OCR tokens": 63.70967741935484, "Total Count of PDF token": 158, "name": "63.71%"}, {"pdf_letters": "'\\\\xad'", "ocr_letters": "INSERT", "% of all OCR tokens": 86.43507030603806, "Total Count of PDF token": 1045, "name": "86.44%"}, {"pdf_letters": "\u223c", "ocr_letters": "INSERT", "% of all OCR tokens": 21.686746987951807, "Total Count of PDF token": 612, "name": "21.69%"}, {"pdf_letters": "\u223c", "ocr_letters": "~", "% of all OCR tokens": 62.61516654854713, "Total Count of PDF token": 1767, "name": "62.62%"}, {"pdf_letters": "\u223c", "ocr_letters": "\u2014", "% of all OCR tokens": 4.004252303330971, "Total Count of PDF token": 113, "name": "4.0%"}, {"pdf_letters": "\u00d7", "ocr_letters": "\u00ab", "% of all OCR tokens": 12.134251290877797, "Total Count of PDF token": 141, "name": "12.13%"}, {"pdf_letters": "\u00d7", "ocr_letters": "INSERT", "% of all OCR tokens": 32.87435456110155, "Total Count of PDF token": 382, "name": "32.87%"}, {"pdf_letters": "\u00d7", "ocr_letters": "x", "% of all OCR tokens": 35.88640275387263, "Total Count of PDF token": 417, "name": "35.89%"}, {"pdf_letters": "\u00c2", "ocr_letters": "INSERT", "% of all OCR tokens": 57.73480662983425, "Total Count of PDF token": 209, "name": "57.73%"}, {"pdf_letters": "\u00c2", "ocr_letters": "A", "% of all OCR tokens": 28.176795580110497, "Total Count of PDF token": 102, "name": "28.18%"}, {"pdf_letters": "\u2299", "ocr_letters": ".", "% of all OCR tokens": 53.09734513274337, "Total Count of PDF token": 240, "name": "53.1%"}, {"pdf_letters": "\u2299", "ocr_letters": "INSERT", "% of all OCR tokens": 22.345132743362832, "Total Count of PDF token": 101, "name": "22.35%"}, {"pdf_letters": "\u03bc", "ocr_letters": "INSERT", "% of all OCR tokens": 26.306620209059233, "Total Count of PDF token": 151, "name": "26.31%"}, {"pdf_letters": "\u03bc", "ocr_letters": "j", "% of all OCR tokens": 18.466898954703833, "Total Count of PDF token": 106, "name": "18.47%"}, {"pdf_letters": "\u0394", "ocr_letters": "A", "% of all OCR tokens": 33.661417322834644, "Total Count of PDF token": 171, "name": "33.66%"}, {"pdf_letters": "\u0394", "ocr_letters": "INSERT", "% of all OCR tokens": 53.14960629921261, "Total Count of PDF token": 270, "name": "53.15%"}, {"pdf_letters": "\u2218", "ocr_letters": "\u00b0", "% of all OCR tokens": 41.795665634674926, "Total Count of PDF token": 135, "name": "41.8%"}, {"pdf_letters": "\u03c4", "ocr_letters": "INSERT", "% of all OCR tokens": 53.66492146596858, "Total Count of PDF token": 205, "name": "53.66%"}, {"pdf_letters": "\u03c0", "ocr_letters": "INSERT", "% of all OCR tokens": 56.018518518518526, "Total Count of PDF token": 121, "name": "56.02%"}, {"pdf_letters": "\u00f6", "ocr_letters": "o", "% of all OCR tokens": 38.8418557399255, "Total Count of PDF token": 1147, "name": "38.84%"}, {"pdf_letters": "\u00f6", "ocr_letters": "\u00f3", "% of all OCR tokens": 44.361666102268885, "Total Count of PDF token": 1310, "name": "44.36%"}, {"pdf_letters": "\u00f6", "ocr_letters": "INSERT", "% of all OCR tokens": 3.995936335929563, "Total Count of PDF token": 118, "name": "4.0%"}, {"pdf_letters": "\u03c3", "ocr_letters": "\u03c3", "% of all OCR tokens": 17.638266068759343, "Total Count of PDF token": 118, "name": "17.64%"}, {"pdf_letters": "\u03c3", "ocr_letters": "o", "% of all OCR tokens": 16.292974588938712, "Total Count of PDF token": 109, "name": "16.29%"}, {"pdf_letters": "\u03c3", "ocr_letters": "INSERT", "% of all OCR tokens": 28.101644245142005, "Total Count of PDF token": 188, "name": "28.1%"}, {"pdf_letters": "\u00e4", "ocr_letters": "\u00e1", "% of all OCR tokens": 11.334002006018054, "Total Count of PDF token": 113, "name": "11.33%"}, {"pdf_letters": "\u00e4", "ocr_letters": "i", "% of all OCR tokens": 12.236710130391174, "Total Count of PDF token": 122, "name": "12.24%"}, {"pdf_letters": "\u00e4", "ocr_letters": "a", "% of all OCR tokens": 51.25376128385155, "Total Count of PDF token": 511, "name": "51.25%"}, {"pdf_letters": "\u00e4", "ocr_letters": "\u00e0", "% of all OCR tokens": 10.230692076228685, "Total Count of PDF token": 102, "name": "10.23%"}, {"pdf_letters": "\u03b1", "ocr_letters": "\u03b1", "% of all OCR tokens": 11.832797427652734, "Total Count of PDF token": 184, "name": "11.83%"}, {"pdf_letters": "\u03b1", "ocr_letters": "INSERT", "% of all OCR tokens": 19.742765273311896, "Total Count of PDF token": 307, "name": "19.74%"}, {"pdf_letters": "\u03b1", "ocr_letters": "o", "% of all OCR tokens": 9.45337620578778, "Total Count of PDF token": 147, "name": "9.45%"}, {"pdf_letters": "\u03b1", "ocr_letters": "a", "% of all OCR tokens": 35.4983922829582, "Total Count of PDF token": 552, "name": "35.5%"}, {"pdf_letters": "\u03a9", "ocr_letters": "INSERT", "% of all OCR tokens": 47.59825327510917, "Total Count of PDF token": 109, "name": "47.6%"}, {"pdf_letters": "\u00ed", "ocr_letters": "\u00ed", "% of all OCR tokens": 34.55056179775281, "Total Count of PDF token": 492, "name": "34.55%"}, {"pdf_letters": "\u00ed", "ocr_letters": "i", "% of all OCR tokens": 40.80056179775281, "Total Count of PDF token": 581, "name": "40.8%"}, {"pdf_letters": "\u00ed", "ocr_letters": "f", "% of all OCR tokens": 8.637640449438203, "Total Count of PDF token": 123, "name": "8.64%"}, {"pdf_letters": "\u00f3", "ocr_letters": "\u00f3", "% of all OCR tokens": 67.00680272108843, "Total Count of PDF token": 788, "name": "67.01%"}, {"pdf_letters": "\u00f3", "ocr_letters": "o", "% of all OCR tokens": 25.34013605442177, "Total Count of PDF token": 298, "name": "25.34%"}, {"pdf_letters": "\u00f8", "ocr_letters": "o", "% of all OCR tokens": 68.58108108108108, "Total Count of PDF token": 203, "name": "68.58%"}, {"pdf_letters": "\u00e8", "ocr_letters": "e", "% of all OCR tokens": 64.33260393873084, "Total Count of PDF token": 294, "name": "64.33%"}, {"pdf_letters": "\u00e8", "ocr_letters": "\u00e9", "% of all OCR tokens": 25.38293216630197, "Total Count of PDF token": 116, "name": "25.38%"}, {"pdf_letters": "\u00f4", "ocr_letters": "o", "% of all OCR tokens": 75.40983606557377, "Total Count of PDF token": 184, "name": "75.41%"}, {"pdf_letters": "\u00e0", "ocr_letters": "\u00e0", "% of all OCR tokens": 66.27218934911244, "Total Count of PDF token": 112, "name": "66.27%"}, {"pdf_letters": "\u0107", "ocr_letters": "\u00e9", "% of all OCR tokens": 66.53225806451613, "Total Count of PDF token": 165, "name": "66.53%"}, {"pdf_letters": "\u03b4", "ocr_letters": "INSERT", "% of all OCR tokens": 42.02453987730061, "Total Count of PDF token": 137, "name": "42.02%"}, {"pdf_letters": "\u2248", "ocr_letters": "z", "% of all OCR tokens": 29.944547134935306, "Total Count of PDF token": 162, "name": "29.94%"}, {"pdf_letters": "\u03b3", "ocr_letters": "INSERT", "% of all OCR tokens": 41.810344827586206, "Total Count of PDF token": 194, "name": "41.81%"}, {"pdf_letters": "\u03b2", "ocr_letters": "INSERT", "% of all OCR tokens": 27.930535455861072, "Total Count of PDF token": 193, "name": "27.93%"}, {"pdf_letters": "\u03bd", "ocr_letters": "INSERT", "% of all OCR tokens": 46.15384615384615, "Total Count of PDF token": 144, "name": "46.15%"}, {"pdf_letters": "\u03c1", "ocr_letters": "INSERT", "% of all OCR tokens": 50.92936802973978, "Total Count of PDF token": 137, "name": "50.93%"}, {"pdf_letters": "\u017a", "ocr_letters": "z", "% of all OCR tokens": 92.17391304347827, "Total Count of PDF token": 106, "name": "92.17%"}, {"pdf_letters": "\u03b8", "ocr_letters": "INSERT", "% of all OCR tokens": 55.61497326203209, "Total Count of PDF token": 104, "name": "55.61%"}, {"pdf_letters": "\u0393", "ocr_letters": "INSERT", "% of all OCR tokens": 69.37984496124031, "Total Count of PDF token": 179, "name": "69.38%"}, {"pdf_letters": "'\\\\t'", "ocr_letters": "INSERT", "% of all OCR tokens": 100.0, "Total Count of PDF token": 2015, "name": "100.0%"}, {"pdf_letters": "\u0142", "ocr_letters": "l", "% of all OCR tokens": 51.867219917012456, "Total Count of PDF token": 125, "name": "51.87%"}, {"pdf_letters": "\u0307", "ocr_letters": "INSERT", "% of all OCR tokens": 70.1219512195122, "Total Count of PDF token": 115, "name": "70.12%"}, {"pdf_letters": "\u27e8", "ocr_letters": "INSERT", "% of all OCR tokens": 72.78481012658227, "Total Count of PDF token": 115, "name": "72.78%"}], "data-081e3fbf9b638105f2f44dea079b8589": [{"Total": "Total % selected (of OCR tokens)="}]}}